Metadata-Version: 2.1
Name: pysolrwrapper
Version: 1.0.0
Summary: A wrapper for pySolr
Home-page: https://framagit.org/parisni/pysolrwrapper
Author: nicolas paris
Author-email: nicolas.paris@riseup.net
License: MIT
Platform: UNKNOWN
Classifier: License :: OSI Approved :: MIT License
Classifier: Programming Language :: Python
Classifier: Programming Language :: Python :: 3
Classifier: Programming Language :: Python :: 3.6
Classifier: Programming Language :: Python :: Implementation :: CPython
Classifier: Programming Language :: Python :: Implementation :: PyPy
Requires-Python: >=3.6.0
